sourcepatterndata.py
sourcepatterndata-1.0.dist-info/licenses/LICENSE.txt
sourcepatterndata-1.0.dist-info/METADATA
sourcepatterndata-1.0.dist-info/WHEEL
sourcepatterndata-1.0.dist-info/top_level.txt
sourcepatterndata-1.0.dist-info/RECORD
