Metadata-Version: 2.4
Name: sourcepatterndata
Version: 1.0
Summary: This is to find the errors in IICS session logs. I have took some patterns to identify the errors
Author-email: Sai Prakash Simhadri <saiprakashsimhadri@gmail.com>
License: MIT
Project-URL: Homepage, https://github.com/saiprakashsimhadri/sourcepatterndata
Requires-Python: >=3.8
License-File: LICENSE.txt
Dynamic: license-file
